{
  "errorCode": 0,
  "totalRows": null,
  "payload": {
    "match": {
      "id": 1285,
      "name": "October 2025 NRL22 @ Hobble Creek",
      "address": "110 Hobble Creek Road",
      "startDate": "2025-10-25 14:30:00",
      "creationDate": "2025-09-30 14:29:59",
      "deleted": false,
      "shootersCount": 20,
      "stagesCount": 5,
      "targetsCount": 54,
      "creatorSocialIdentityId": 807,
      "endDate": "2025-10-25 20:00:00",
      "registrationStartDate": "2025-09-30 13:00:00",
      "registrationEndDate": "2025-10-25 16:00:00",
      "emailsOnRegistrationChanges": false,
      "maxShooters": 60,
      "address2": "",
      "city": "Springville",
      "state": "Utah",
      "usState": {
        "id": 159,
        "name": "Utah",
        "code": "UT",
        "countryId": null
      },
      "country": {
        "id": 2,
        "name": "United States",
        "countryImageName": null,
        "countryCodeAlphaTwo": null,
        "countryCodeAlphaThree": null,
        "countryCodePhone": null,
        "signupAllowed": null
      },
      "zipCode": "84663",
      "about": "October NRL22 Match! Come check us out! Loaner rifles available. Shop www.NextShotPrecision.com",
      "matchResultsHidden": false,
      "matchPrivate": false,
      "availableSpotsHidden": false,
      "paymentsOnline": true,
      "price": "25",
      "priceDonation": "0",
      "clubMembersPrice": "0.00",
      "emailBodyRegistrationApproved": "",
      "emailBodyRegistrationRejected": "",
      "seriesId": 4,
      "clubId": 65,
      "matchType": "RIMFIRE",
      "matchQualifier": false,
      "matchFinal": false,
      "venmoUsername": null,
      "regionId": null,
      "maxPoints": 5400,
      "multiplier": 10,
      "mulligansPerCompetitor": 0,
      "testMatch": false,
      "logoFileId": "1759242537843-6cqf2d6d3xl0saxu.png",
      "hasParTimeBonus": true,
      "allowsBonusStages": true,
      "usesCurveScoring": false,
      "usesClubCurveScoring": false,
      "maxCurvePoints": null,
      "paymentRequiredToRegister": true,
      "priceCurrencyId": 1,
      "maxShootersPerSquad": 8,
      "limitSquadSize": true,
      "registrationCustomizations": false,
      "customDivisions": false,
      "customClassifications": false,
      "customCategories": false,
      "allowTeams": false,
      "teamsRequired": false,
      "requirePhoneNumber": false,
      "showShirtSizeField": false,
      "powerFactorTieBreaker": false,
      "deadTargetSystem": false,
      "waiverEnabled": false,
      "waiver": "",
      "codesEnabled": false,
      "codesStartDate": null,
      "codesEndDate": null,
      "discountCodesEnabled": false,
      "registrationEnabled": true,
      "timePlus": false,
      "timePenalty1Name": null,
      "timePenalty1Value": null,
      "timePenalty2Name": null,
      "timePenalty2Value": null,
      "timePenalty3Name": null,
      "timePenalty3Value": null,
      "timePenalty4Name": null,
      "timePenalty4Value": null,
      "timePenalty5Name": null,
      "timePenalty5Value": null,
      "timePenalty6Name": null,
      "timePenalty6Value": null,
      "targetMissPenaltyValue": 0,
      "failureToEngagePenaltyValue": 0,
      "squaddingLocked": false,
      "developmentMatch": false,
      "podium": null,
      "logoImage": {
        "identityId": 807,
        "fileId": "1759242537843-6cqf2d6d3xl0saxu.png",
        "thumbnailUrl": "https://impactscoring-social-bucket-production2.s3.amazonaws.com/matches/807/256-1759242537843-6cqf2d6d3xl0saxu.png",
        "previewUrl": "https://impactscoring-social-bucket-production2.s3.amazonaws.com/matches/807/512-1759242537843-6cqf2d6d3xl0saxu.png",
        "bigUrl": "https://impactscoring-social-bucket-production2.s3.amazonaws.com/matches/807/1024-1759242537843-6cqf2d6d3xl0saxu.png",
        "veryBigUrl": "https://impactscoring-social-bucket-production2.s3.amazonaws.com/matches/807/2048-1759242537843-6cqf2d6d3xl0saxu.png",
        "originalUrl": "https://impactscoring-social-bucket-production2.s3.amazonaws.com/matches/807/original-1759242537843-6cqf2d6d3xl0saxu.png",
        "videoOriginalS3Path": null,
        "videoProcessedFolderS3Path": null,
        "videoOriginalUrl": null,
        "videoProcessedFolderUrl": null,
        "videoProcessedAppleUrl": null,
        "videoProcessedAndroidUrl": null,
        "audioUrl": null,
        "audioProcessedUrl": null,
        "audioS3path": null,
        "fileWidth": null,
        "fileHeight": null,
        "fileLength": null,
        "audioSamples": null,
        "fileType": "IMAGE"
      },
      "clubLogoImage": {
        "identityId": 807,
        "fileId": "1728014298842-bhoqu96mz5yivif9.png",
        "thumbnailUrl": null,
        "previewUrl": null,
        "bigUrl": null,
        "veryBigUrl": null,
        "originalUrl": null,
        "videoOriginalS3Path": null,
        "videoProcessedFolderS3Path": null,
        "videoOriginalUrl": null,
        "videoProcessedFolderUrl": null,
        "videoProcessedAppleUrl": null,
        "videoProcessedAndroidUrl": null,
        "audioUrl": null,
        "audioProcessedUrl": null,
        "audioS3path": null,
        "fileWidth": null,
        "fileHeight": null,
        "fileLength": null,
        "audioSamples": null,
        "fileType": null
      },
      "registeredForMatch": null,
      "matchStarted": true,
      "matchEnded": true,
      "registrationStarted": true,
      "registrationEnded": true,
      "registrationWithCodesStarted": false,
      "registrationWithCodesEnded": false,
      "isRangeOfficer": null,
      "matchTypeReadableName": "Rimfire",
      "seriesName": "NRL22 Series",
      "isMatchDirector": null,
      "impactsColumnName": "MATCH TOTAL",
      "stageImpactsColumnName": "STAGE TOTAL",
      "impactsWithoutBonusColumnName": null,
      "proPointsColumnName": null,
      "hasBonusStages": false,
      "hasProPoints": false,
      "hasScoreColumn": true,
      "defaultClassificationId": 9,
      "priceCurrencyCode": "USD",
      "priceFormatted": null,
      "priceFormat": null,
      "canChangeTargetPointValue": true,
      "requireCountry": false,
      "liveStreamingIsLive": false,
      "liveStreamingPlaybackUrl": null,
      "liveStreamingThumbnailUrl": null,
      "clonedFromMatchId": null
    },
    "shooters": [
      {
        "id": 1825,
        "name": "Jarom Leavitt",
        "handleName": "22lrShooter",
        "profileImage": {
          "identityId": 1825,
          "fileId": "1732423708826-c3w3e9d2d1bssayf.jpg",
          "thumbnailUrl": "https://impactscoring-social-bucket-production2.s3.amazonaws.com/profileImages/1825/256-1732423708826-c3w3e9d2d1bssayf.jpg",
          "previewUrl": "https://impactscoring-social-bucket-production2.s3.amazonaws.com/profileImages/1825/512-1732423708826-c3w3e9d2d1bssayf.jpg",
          "bigUrl": "https://impactscoring-social-bucket-production2.s3.amazonaws.com/profileImages/1825/1024-1732423708826-c3w3e9d2d1bssayf.jpg",
          "veryBigUrl": "https://impactscoring-social-bucket-production2.s3.amazonaws.com/profileImages/1825/2048-1732423708826-c3w3e9d2d1bssayf.jpg",
          "originalUrl": "https://impactscoring-social-bucket-production2.s3.amazonaws.com/profileImages/1825/original-1732423708826-c3w3e9d2d1bssayf.jpg",
          "videoOriginalS3Path": null,
          "videoProcessedFolderS3Path": null,
          "videoOriginalUrl": null,
          "videoProcessedFolderUrl": null,
          "videoProcessedAppleUrl": null,
          "videoProcessedAndroidUrl": null,
          "audioUrl": null,
          "audioProcessedUrl": null,
          "audioS3path": null,
          "fileWidth": null,
          "fileHeight": null,
          "fileLength": null,
          "audioSamples": null,
          "fileType": "IMAGE"
        },
        "city": null,
        "state": null,
        "email": "jleavitt73@yahoo.com",
        "firstName": "Jarom",
        "lastName": "Leavitt",
        "divisionName": null,
        "classificationName": null,
        "addedToMatch": null,
        "addedToSquad": null,
        "points": 52000,
        "tieBreakerPoints": 1200,
        "pointsForNonBonusStages": 52000,
        "hundredsOfSecond": 9000,
        "tieBreakerHundredsOfSecond": 9000,
        "squadId": 3840,
        "squadUuid": null,
        "stageId": null,
        "stageUuid": null,
        "divisionId": 1,
        "maxPoints": 54000,
        "stagesProgressCount": 5,
        "stagesCount": 5,
        "shotsProgressCount": 54,
        "maxShots": 54,
        "stageCompleted": null,
        "stageDisqualified": false,
        "matchDisqualified": false,
        "bonusPoints10k": 30000,
        "bonusPoints10kForNonBonusStages": 30000,
        "allSquads": null,
        "allStages": null,
        "categoryIds": null,
        "classificationId": 6,
        "memberNumber": "197",
        "proSeriesPoints10k": null,
        "requiresTime": null,
        "rank": 1,
        "successRate": null,
        "squad": null,
        "amount": 0,
        "currencyCode": null,
        "formattedAmount": null,
        "paymentSuccessful": null,
        "paymentFailed": null,
        "paymentProcessing": null,
        "paymentRefunded": null,
        "paymentRefundProcessing": null,
        "paymentDate": null,
        "matchShooterId": null,
        "isShootingNow": false,
        "isShootingNext": false,
        "hidden": null,
        "isInTeam": null,
        "teamName": null,
        "shootAsTeam": false,
        "teammateShooterId": null,
        "secondShooter": null,
        "powerFactor": null,
        "isMD": null,
        "isRO": null,
        "countryId": 2,
        "countryCode": "US",
        "dropped": -2000,
        "shirtSize": null,
        "individualName": null,
        "individualHandleName": null,
        "following": false,
        "checkedIn": null,
        "penaltiesHundredsOfSecond": 0,
        "bonusesHundredsOfSecond": 0,
        "totalTimeHundredsOfSecond": null,
        "misses": 2,
        "shotsNotFired": 0,
        "timePenalty1Count": null,
        "timePenalty2Count": null,
        "timePenalty3Count": null,
        "timePenalty4Count": null,
        "timePenalty5Count": null,
        "timePenalty6Count": null,
        "targetsCount": null,
        "isMe": null,
        "awardHeader": null
      },
      {
        "id": 773,
        "name": "David Civello",
        "handleName": "LongRyfle",
        "profileImage": {
          "identityId": 773,
          "fileId": "1729793952253-u85y41ihzrsxnglk.jpg",
          "thumbnailUrl": "https://impactscoring-social-bucket-production2.s3.amazonaws.com/profileImages/773/256-1729793952253-u85y41ihzrsxnglk.jpg",
          "previewUrl": "https://impactscoring-social-bucket-production2.s3.amazonaws.com/profileImages/773/512-1729793952253-u85y41ihzrsxnglk.jpg",
          "bigUrl": "https://impactscoring-social-bucket-production2.s3.amazonaws.com/profileImages/773/1024-1729793952253-u85y41ihzrsxnglk.jpg",
          "veryBigUrl": "https://impactscoring-social-bucket-production2.s3.amazonaws.com/profileImages/773/2048-1729793952253-u85y41ihzrsxnglk.jpg",
          "originalUrl": "https://impactscoring-social-bucket-production2.s3.amazonaws.com/profileImages/773/original-1729793952253-u85y41ihzrsxnglk.jpg",
          "videoOriginalS3Path": null,
          "videoProcessedFolderS3Path": null,
          "videoOriginalUrl": null,
          "videoProcessedFolderUrl": null,
          "videoProcessedAppleUrl": null,
          "videoProcessedAndroidUrl": null,
          "audioUrl": null,
          "audioProcessedUrl": null,
          "audioS3path": null,
          "fileWidth": null,
          "fileHeight": null,
          "fileLength": null,
          "audioSamples": null,
          "fileType": "IMAGE"
        },
        "city": null,
        "state": "Utah",
        "email": "david.civello.88@gmail.com",
        "firstName": "David",
        "lastName": "Civello",
        "divisionName": null,
        "classificationName": null,
        "addedToMatch": null,
        "addedToSquad": null,
        "points": 51000,
        "tieBreakerPoints": 1200,
        "pointsForNonBonusStages": 51000,
        "hundredsOfSecond": 5100,
        "tieBreakerHundredsOfSecond": 5100,
        "squadId": 3839,
        "squadUuid": null,
        "stageId": null,
        "stageUuid": null,
        "divisionId": 1,
        "maxPoints": 54000,
        "stagesProgressCount": 5,
        "stagesCount": 5,
        "shotsProgressCount": 54,
        "maxShots": 54,
        "stageCompleted": null,
        "stageDisqualified": false,
        "matchDisqualified": false,
        "bonusPoints10k": 69000,
        "bonusPoints10kForNonBonusStages": 69000,
        "allSquads": null,
        "allStages": null,
        "categoryIds": null,
        "classificationId": 5,
        "memberNumber": "2037",
        "proSeriesPoints10k": null,
        "requiresTime": null,
        "rank": 2,
        "successRate": null,
        "squad": null,
        "amount": 0,
        "currencyCode": null,
        "formattedAmount": null,
        "paymentSuccessful": null,
        "paymentFailed": null,
        "paymentProcessing": null,
        "paymentRefunded": null,
        "paymentRefundProcessing": null,
        "paymentDate": null,
        "matchShooterId": null,
        "isShootingNow": false,
        "isShootingNext": false,
        "hidden": null,
        "isInTeam": null,
        "teamName": null,
        "shootAsTeam": false,
        "teammateShooterId": null,
        "secondShooter": null,
        "powerFactor": null,
        "isMD": null,
        "isRO": null,
        "countryId": 2,
        "countryCode": "US",
        "dropped": -3000,
        "shirtSize": null,
        "individualName": null,
        "individualHandleName": null,
        "following": false,
        "checkedIn": null,
        "penaltiesHundredsOfSecond": 0,
        "bonusesHundredsOfSecond": 0,
        "totalTimeHundredsOfSecond": null,
        "misses": 3,
        "shotsNotFired": 0,
        "timePenalty1Count": null,
        "timePenalty2Count": null,
        "timePenalty3Count": null,
        "timePenalty4Count": null,
        "timePenalty5Count": null,
        "timePenalty6Count": null,
        "targetsCount": null,
        "isMe": null,
        "awardHeader": null
      },
      {
        "id": 870,
        "name": "Carson Zenger",
        "handleName": "WootMaster",
        "profileImage": {
          "identityId": 870,
          "fileId": "1742046613318-n4r7yxp2gbc5ij5n.jpg",
          "thumbnailUrl": "https://impactscoring-social-bucket-production2.s3.amazonaws.com/profileImages/870/256-1742046613318-n4r7yxp2gbc5ij5n.jpg",
          "previewUrl": "https://impactscoring-social-bucket-production2.s3.amazonaws.com/profileImages/870/512-1742046613318-n4r7yxp2gbc5ij5n.jpg",
          "bigUrl": "https://impactscoring-social-bucket-production2.s3.amazonaws.com/profileImages/870/1024-1742046613318-n4r7yxp2gbc5ij5n.jpg",
          "veryBigUrl": "https://impactscoring-social-bucket-production2.s3.amazonaws.com/profileImages/870/2048-1742046613318-n4r7yxp2gbc5ij5n.jpg",
          "originalUrl": "https://impactscoring-social-bucket-production2.s3.amazonaws.com/profileImages/870/original-1742046613318-n4r7yxp2gbc5ij5n.jpg",
          "videoOriginalS3Path": null,
          "videoProcessedFolderS3Path": null,
          "videoOriginalUrl": null,
          "videoProcessedFolderUrl": null,
          "videoProcessedAppleUrl": null,
          "videoProcessedAndroidUrl": null,
          "audioUrl": null,
          "audioProcessedUrl": null,
          "audioS3path": null,
          "fileWidth": null,
          "fileHeight": null,
          "fileLength": null,
          "audioSamples": null,
          "fileType": "IMAGE"
        },
        "city": null,
        "state": null,
        "email": "carson553@hotmail.com",
        "firstName": "Carson",
        "lastName": "Zenger",
        "divisionName": null,
        "classificationName": null,
        "addedToMatch": null,
        "addedToSquad": null,
        "points": 49000,
        "tieBreakerPoints": 1200,
        "pointsForNonBonusStages": 49000,
        "hundredsOfSecond": 6700,
        "tieBreakerHundredsOfSecond": 6700,
        "squadId": 3841,
        "squadUuid": null,
        "stageId": null,
        "stageUuid": null,
        "divisionId": 1,
        "maxPoints": 54000,
        "stagesProgressCount": 5,
        "stagesCount": 5,
        "shotsProgressCount": 54,
        "maxShots": 54,
        "stageCompleted": null,
        "stageDisqualified": false,
        "matchDisqualified": false,
        "bonusPoints10k": 53000,
        "bonusPoints10kForNonBonusStages": 53000,
        "allSquads": null,
        "allStages": null,
        "categoryIds": null,
        "classificationId": 6,
        "memberNumber": "3843",
        "proSeriesPoints10k": null,
        "requiresTime": null,
        "rank": 3,
        "successRate": null,
        "squad": null,
        "amount": 0,
        "currencyCode": null,
        "formattedAmount": null,
        "paymentSuccessful": null,
        "paymentFailed": null,
        "paymentProcessing": null,
        "paymentRefunded": null,
        "paymentRefundProcessing": null,
        "paymentDate": null,
        "matchShooterId": null,
        "isShootingNow": false,
        "isShootingNext": false,
        "hidden": null,
        "isInTeam": null,
        "teamName": null,
        "shootAsTeam": false,
        "teammateShooterId": null,
        "secondShooter": null,
        "powerFactor": null,
        "isMD": null,
        "isRO": null,
        "countryId": 2,
        "countryCode": "US",
        "dropped": -5000,
        "shirtSize": null,
        "individualName": null,
        "individualHandleName": null,
        "following": false,
        "checkedIn": null,
        "penaltiesHundredsOfSecond": 0,
        "bonusesHundredsOfSecond": 0,
        "totalTimeHundredsOfSecond": null,
        "misses": 5,
        "shotsNotFired": 0,
        "timePenalty1Count": null,
        "timePenalty2Count": null,
        "timePenalty3Count": null,
        "timePenalty4Count": null,
        "timePenalty5Count": null,
        "timePenalty6Count": null,
        "targetsCount": null,
        "isMe": null,
        "awardHeader": null
      },
      {
        "id": 5754,
        "name": "Boyd Linder",
        "handleName": "utahpewpew",
        "profileImage": {
          "identityId": 5754,
          "fileId": "1753488364739-6ludkdmljcmucj4t.jpg",
          "thumbnailUrl": "https://impactscoring-social-bucket-production2.s3.amazonaws.com/profileImages/5754/256-1753488364739-6ludkdmljcmucj4t.jpg",
          "previewUrl": "https://impactscoring-social-bucket-production2.s3.amazonaws.com/profileImages/5754/512-1753488364739-6ludkdmljcmucj4t.jpg",
          "bigUrl": "https://impactscoring-social-bucket-production2.s3.amazonaws.com/profileImages/5754/1024-1753488364739-6ludkdmljcmucj4t.jpg",
          "veryBigUrl": "https://impactscoring-social-bucket-production2.s3.amazonaws.com/profileImages/5754/2048-1753488364739-6ludkdmljcmucj4t.jpg",
          "originalUrl": "https://impactscoring-social-bucket-production2.s3.amazonaws.com/profileImages/5754/original-1753488364739-6ludkdmljcmucj4t.jpg",
          "videoOriginalS3Path": null,
          "videoProcessedFolderS3Path": null,
          "videoOriginalUrl": null,
          "videoProcessedFolderUrl": null,
          "videoProcessedAppleUrl": null,
          "videoProcessedAndroidUrl": null,
          "audioUrl": null,
          "audioProcessedUrl": null,
          "audioS3path": null,
          "fileWidth": null,
          "fileHeight": null,
          "fileLength": null,
          "audioSamples": null,
          "fileType": "IMAGE"
        },
        "city": null,
        "state": null,
        "email": "utahpewpew@gmail.com",
        "firstName": "Boyd",
        "lastName": "Linder",
        "divisionName": null,
        "classificationName": null,
        "addedToMatch": null,
        "addedToSquad": null,
        "points": 47000,
        "tieBreakerPoints": 1100,
        "pointsForNonBonusStages": 47000,
        "hundredsOfSecond": 5700,
        "tieBreakerHundredsOfSecond": 5700,
        "squadId": 3842,
        "squadUuid": null,
        "stageId": null,
        "stageUuid": null,
        "divisionId": 3,
        "maxPoints": 54000,
        "stagesProgressCount": 5,
        "stagesCount": 5,
        "shotsProgressCount": 54,
        "maxShots": 54,
        "stageCompleted": null,
        "stageDisqualified": false,
        "matchDisqualified": false,
        "bonusPoints10k": 63000,
        "bonusPoints10kForNonBonusStages": 63000,
        "allSquads": null,
        "allStages": null,
        "categoryIds": null,
        "classificationId": 5,
        "memberNumber": "969",
        "proSeriesPoints10k": null,
        "requiresTime": null,
        "rank": 4,
        "successRate": null,
        "squad": null,
        "amount": 0,
        "currencyCode": null,
        "formattedAmount": null,
        "paymentSuccessful": null,
        "paymentFailed": null,
        "paymentProcessing": null,
        "paymentRefunded": null,
        "paymentRefundProcessing": null,
        "paymentDate": null,
        "matchShooterId": null,
        "isShootingNow": false,
        "isShootingNext": false,
        "hidden": null,
        "isInTeam": null,
        "teamName": null,
        "shootAsTeam": false,
        "teammateShooterId": null,
        "secondShooter": null,
        "powerFactor": null,
        "isMD": null,
        "isRO": null,
        "countryId": null,
        "countryCode": null,
        "dropped": -7000,
        "shirtSize": null,
        "individualName": null,
        "individualHandleName": null,
        "following": false,
        "checkedIn": null,
        "penaltiesHundredsOfSecond": 0,
        "bonusesHundredsOfSecond": 0,
        "totalTimeHundredsOfSecond": null,
        "misses": 7,
        "shotsNotFired": 0,
        "timePenalty1Count": null,
        "timePenalty2Count": null,
        "timePenalty3Count": null,
        "timePenalty4Count": null,
        "timePenalty5Count": null,
        "timePenalty6Count": null,
        "targetsCount": null,
        "isMe": null,
        "awardHeader": null
      },
      {
        "id": 923,
        "name": "Levi Cress",
        "handleName": "LeviCress",
        "profileImage": {
          "identityId": 923,
          "fileId": "1731389976727-8c9o8tqgwlvszp3a.jpg",
          "thumbnailUrl": "https://impactscoring-social-bucket-production2.s3.amazonaws.com/profileImages/923/256-1731389976727-8c9o8tqgwlvszp3a.jpg",
          "previewUrl": "https://impactscoring-social-bucket-production2.s3.amazonaws.com/profileImages/923/512-1731389976727-8c9o8tqgwlvszp3a.jpg",
          "bigUrl": "https://impactscoring-social-bucket-production2.s3.amazonaws.com/profileImages/923/1024-1731389976727-8c9o8tqgwlvszp3a.jpg",
          "veryBigUrl": "https://impactscoring-social-bucket-production2.s3.amazonaws.com/profileImages/923/2048-1731389976727-8c9o8tqgwlvszp3a.jpg",
          "originalUrl": "https://impactscoring-social-bucket-production2.s3.amazonaws.com/profileImages/923/original-1731389976727-8c9o8tqgwlvszp3a.jpg",
          "videoOriginalS3Path": null,
          "videoProcessedFolderS3Path": null,
          "videoOriginalUrl": null,
          "videoProcessedFolderUrl": null,
          "videoProcessedAppleUrl": null,
          "videoProcessedAndroidUrl": null,
          "audioUrl": null,
          "audioProcessedUrl": null,
          "audioS3path": null,
          "fileWidth": null,
          "fileHeight": null,
          "fileLength": null,
          "audioSamples": null,
          "fileType": "IMAGE"
        },
        "city": "Lehi",
        "state": "Utah",
        "email": "levicress@hotmail.com",
        "firstName": "Levi",
        "lastName": "Cress",
        "divisionName": null,
        "classificationName": null,
        "addedToMatch": null,
        "addedToSquad": null,
        "points": 46000,
        "tieBreakerPoints": 1000,
        "pointsForNonBonusStages": 46000,
        "hundredsOfSecond": 9600,
        "tieBreakerHundredsOfSecond": 9600,
        "squadId": 3841,
        "squadUuid": null,
        "stageId": null,
        "stageUuid": null,
        "divisionId": 1,
        "maxPoints": 54000,
        "stagesProgressCount": 5,
        "stagesCount": 5,
        "shotsProgressCount": 52,
        "maxShots": 54,
        "stageCompleted": null,
        "stageDisqualified": false,
        "matchDisqualified": false,
        "bonusPoints10k": 24000,
        "bonusPoints10kForNonBonusStages": 24000,
        "allSquads": null,
        "allStages": null,
        "categoryIds": null,
        "classificationId": 5,
        "memberNumber": "2008",
        "proSeriesPoints10k": null,
        "requiresTime": null,
        "rank": 5,
        "successRate": null,
        "squad": null,
        "amount": 0,
        "currencyCode": null,
        "formattedAmount": null,
        "paymentSuccessful": null,
        "paymentFailed": null,
        "paymentProcessing": null,
        "paymentRefunded": null,
        "paymentRefundProcessing": null,
        "paymentDate": null,
        "matchShooterId": null,
        "isShootingNow": false,
        "isShootingNext": false,
        "hidden": null,
        "isInTeam": null,
        "teamName": null,
        "shootAsTeam": false,
        "teammateShooterId": null,
        "secondShooter": null,
        "powerFactor": null,
        "isMD": null,
        "isRO": null,
        "countryId": 2,
        "countryCode": "US",
        "dropped": -8000,
        "shirtSize": null,
        "individualName": null,
        "individualHandleName": null,
        "following": false,
        "checkedIn": null,
        "penaltiesHundredsOfSecond": 0,
        "bonusesHundredsOfSecond": 0,
        "totalTimeHundredsOfSecond": null,
        "misses": 6,
        "shotsNotFired": 2,
        "timePenalty1Count": null,
        "timePenalty2Count": null,
        "timePenalty3Count": null,
        "timePenalty4Count": null,
        "timePenalty5Count": null,
        "timePenalty6Count": null,
        "targetsCount": null,
        "isMe": null,
        "awardHeader": null
      },
      {
        "id": 935,
        "name": "Timothy Gillingham",
        "handleName": "Hammer",
        "profileImage": {
          "identityId": 935,
          "fileId": null,
          "thumbnailUrl": null,
          "previewUrl": null,
          "bigUrl": null,
          "veryBigUrl": null,
          "originalUrl": null,
          "videoOriginalS3Path": null,
          "videoProcessedFolderS3Path": null,
          "videoOriginalUrl": null,
          "videoProcessedFolderUrl": null,
          "videoProcessedAppleUrl": null,
          "videoProcessedAndroidUrl": null,
          "audioUrl": null,
          "audioProcessedUrl": null,
          "audioS3path": null,
          "fileWidth": null,
          "fileHeight": null,
          "fileLength": null,
          "audioSamples": null,
          "fileType": "IMAGE"
        },
        "city": null,
        "state": null,
        "email": "gillinghamt@goldtip.com",
        "firstName": "Timothy",
        "lastName": "Gillingham",
        "divisionName": null,
        "classificationName": null,
        "addedToMatch": null,
        "addedToSquad": null,
        "points": 41000,
        "tieBreakerPoints": 1100,
        "pointsForNonBonusStages": 41000,
        "hundredsOfSecond": 8300,
        "tieBreakerHundredsOfSecond": 8300,
        "squadId": 3839,
        "squadUuid": null,
        "stageId": null,
        "stageUuid": null,
        "divisionId": 14,
        "maxPoints": 54000,
        "stagesProgressCount": 5,
        "stagesCount": 5,
        "shotsProgressCount": 54,
        "maxShots": 54,
        "stageCompleted": null,
        "stageDisqualified": false,
        "matchDisqualified": false,
        "bonusPoints10k": 37000,
        "bonusPoints10kForNonBonusStages": 37000,
        "allSquads": null,
        "allStages": null,
        "categoryIds": null,
        "classificationId": 5,
        "memberNumber": "1454",
        "proSeriesPoints10k": null,
        "requiresTime": null,
        "rank": 6,
        "successRate": null,
        "squad": null,
        "amount": 0,
        "currencyCode": null,
        "formattedAmount": null,
        "paymentSuccessful": null,
        "paymentFailed": null,
        "paymentProcessing": null,
        "paymentRefunded": null,
        "paymentRefundProcessing": null,
        "paymentDate": null,
        "matchShooterId": null,
        "isShootingNow": false,
        "isShootingNext": false,
        "hidden": null,
        "isInTeam": null,
        "teamName": null,
        "shootAsTeam": false,
        "teammateShooterId": null,
        "secondShooter": null,
        "powerFactor": null,
        "isMD": null,
        "isRO": null,
        "countryId": null,
        "countryCode": null,
        "dropped": -13000,
        "shirtSize": null,
        "individualName": null,
        "individualHandleName": null,
        "following": false,
        "checkedIn": null,
        "penaltiesHundredsOfSecond": 0,
        "bonusesHundredsOfSecond": 0,
        "totalTimeHundredsOfSecond": null,
        "misses": 13,
        "shotsNotFired": 0,
        "timePenalty1Count": null,
        "timePenalty2Count": null,
        "timePenalty3Count": null,
        "timePenalty4Count": null,
        "timePenalty5Count": null,
        "timePenalty6Count": null,
        "targetsCount": null,
        "isMe": null,
        "awardHeader": null
      },
      {
        "id": 807,
        "name": "Jim Cannon ",
        "handleName": "22lrMarksmen",
        "profileImage": {
          "identityId": 807,
          "fileId": "1728015580211-c93owz6wen3qs0ho.jpg",
          "thumbnailUrl": "https://impactscoring-social-bucket-production2.s3.amazonaws.com/profileImages/807/256-1728015580211-c93owz6wen3qs0ho.jpg",
          "previewUrl": "https://impactscoring-social-bucket-production2.s3.amazonaws.com/profileImages/807/512-1728015580211-c93owz6wen3qs0ho.jpg",
          "bigUrl": "https://impactscoring-social-bucket-production2.s3.amazonaws.com/profileImages/807/1024-1728015580211-c93owz6wen3qs0ho.jpg",
          "veryBigUrl": "https://impactscoring-social-bucket-production2.s3.amazonaws.com/profileImages/807/2048-1728015580211-c93owz6wen3qs0ho.jpg",
          "originalUrl": "https://impactscoring-social-bucket-production2.s3.amazonaws.com/profileImages/807/original-1728015580211-c93owz6wen3qs0ho.jpg",
          "videoOriginalS3Path": null,
          "videoProcessedFolderS3Path": null,
          "videoOriginalUrl": null,
          "videoProcessedFolderUrl": null,
          "videoProcessedAppleUrl": null,
          "videoProcessedAndroidUrl": null,
          "audioUrl": null,
          "audioProcessedUrl": null,
          "audioS3path": null,
          "fileWidth": null,
          "fileHeight": null,
          "fileLength": null,
          "audioSamples": null,
          "fileType": "IMAGE"
        },
        "city": "Springville",
        "state": "Utah",
        "email": "22lrmarksmen@gmail.com",
        "firstName": "Jim",
        "lastName": "Cannon ",
        "divisionName": null,
        "classificationName": null,
        "addedToMatch": null,
        "addedToSquad": null,
        "points": 39000,
        "tieBreakerPoints": 1000,
        "pointsForNonBonusStages": 39000,
        "hundredsOfSecond": 5225,
        "tieBreakerHundredsOfSecond": 5225,
        "squadId": 3842,
        "squadUuid": null,
        "stageId": null,
        "stageUuid": null,
        "divisionId": 1,
        "maxPoints": 54000,
        "stagesProgressCount": 5,
        "stagesCount": 5,
        "shotsProgressCount": 54,
        "maxShots": 54,
        "stageCompleted": null,
        "stageDisqualified": false,
        "matchDisqualified": false,
        "bonusPoints10k": 67750,
        "bonusPoints10kForNonBonusStages": 67750,
        "allSquads": null,
        "allStages": null,
        "categoryIds": null,
        "classificationId": 9,
        "memberNumber": "80",
        "proSeriesPoints10k": null,
        "requiresTime": null,
        "rank": 7,
        "successRate": null,
        "squad": null,
        "amount": 0,
        "currencyCode": null,
        "formattedAmount": null,
        "paymentSuccessful": null,
        "paymentFailed": null,
        "paymentProcessing": null,
        "paymentRefunded": null,
        "paymentRefundProcessing": null,
        "paymentDate": null,
        "matchShooterId": null,
        "isShootingNow": false,
        "isShootingNext": false,
        "hidden": null,
        "isInTeam": null,
        "teamName": null,
        "shootAsTeam": false,
        "teammateShooterId": null,
        "secondShooter": null,
        "powerFactor": null,
        "isMD": null,
        "isRO": null,
        "countryId": 2,
        "countryCode": "US",
        "dropped": -15000,
        "shirtSize": null,
        "individualName": null,
        "individualHandleName": null,
        "following": false,
        "checkedIn": null,
        "penaltiesHundredsOfSecond": 0,
        "bonusesHundredsOfSecond": 0,
        "totalTimeHundredsOfSecond": null,
        "misses": 15,
        "shotsNotFired": 0,
        "timePenalty1Count": null,
        "timePenalty2Count": null,
        "timePenalty3Count": null,
        "timePenalty4Count": null,
        "timePenalty5Count": null,
        "timePenalty6Count": null,
        "targetsCount": null,
        "isMe": null,
        "awardHeader": null
      },
      {
        "id": 2761,
        "name": "Brinley Buhler ",
        "handleName": "rusticcowgals",
        "profileImage": {
          "identityId": 2761,
          "fileId": "1765082219509-qe2vhrjnfkdw81wv.jpg",
          "thumbnailUrl": "https://impactscoring-social-bucket-production2.s3.amazonaws.com/profileImages/2761/256-1765082219509-qe2vhrjnfkdw81wv.jpg",
          "previewUrl": "https://impactscoring-social-bucket-production2.s3.amazonaws.com/profileImages/2761/512-1765082219509-qe2vhrjnfkdw81wv.jpg",
          "bigUrl": "https://impactscoring-social-bucket-production2.s3.amazonaws.com/profileImages/2761/1024-1765082219509-qe2vhrjnfkdw81wv.jpg",
          "veryBigUrl": "https://impactscoring-social-bucket-production2.s3.amazonaws.com/profileImages/2761/2048-1765082219509-qe2vhrjnfkdw81wv.jpg",
          "originalUrl": "https://impactscoring-social-bucket-production2.s3.amazonaws.com/profileImages/2761/original-1765082219509-qe2vhrjnfkdw81wv.jpg",
          "videoOriginalS3Path": null,
          "videoProcessedFolderS3Path": null,
          "videoOriginalUrl": null,
          "videoProcessedFolderUrl": null,
          "videoProcessedAppleUrl": null,
          "videoProcessedAndroidUrl": null,
          "audioUrl": null,
          "audioProcessedUrl": null,
          "audioS3path": null,
          "fileWidth": null,
          "fileHeight": null,
          "fileLength": null,
          "audioSamples": null,
          "fileType": "IMAGE"
        },
        "city": null,
        "state": null,
        "email": "bballstar923@gmail.com",
        "firstName": "Brinley",
        "lastName": "Buhler ",
        "divisionName": null,
        "classificationName": null,
        "addedToMatch": null,
        "addedToSquad": null,
        "points": 39000,
        "tieBreakerPoints": 1200,
        "pointsForNonBonusStages": 39000,
        "hundredsOfSecond": 10900,
        "tieBreakerHundredsOfSecond": 10900,
        "squadId": 3841,
        "squadUuid": null,
        "stageId": null,
        "stageUuid": null,
        "divisionId": 5,
        "maxPoints": 54000,
        "stagesProgressCount": 5,
        "stagesCount": 5,
        "shotsProgressCount": 52,
        "maxShots": 54,
        "stageCompleted": null,
        "stageDisqualified": false,
        "matchDisqualified": false,
        "bonusPoints10k": 11000,
        "bonusPoints10kForNonBonusStages": 11000,
        "allSquads": null,
        "allStages": null,
        "categoryIds": null,
        "classificationId": 9,
        "memberNumber": "",
        "proSeriesPoints10k": null,
        "requiresTime": null,
        "rank": 8,
        "successRate": null,
        "squad": null,
        "amount": 0,
        "currencyCode": null,
        "formattedAmount": null,
        "paymentSuccessful": null,
        "paymentFailed": null,
        "paymentProcessing": null,
        "paymentRefunded": null,
        "paymentRefundProcessing": null,
        "paymentDate": null,
        "matchShooterId": null,
        "isShootingNow": false,
        "isShootingNext": false,
        "hidden": null,
        "isInTeam": null,
        "teamName": null,
        "shootAsTeam": false,
        "teammateShooterId": null,
        "secondShooter": null,
        "powerFactor": null,
        "isMD": null,
        "isRO": null,
        "countryId": 2,
        "countryCode": "US",
        "dropped": -15000,
        "shirtSize": null,
        "individualName": null,
        "individualHandleName": null,
        "following": false,
        "checkedIn": null,
        "penaltiesHundredsOfSecond": 0,
        "bonusesHundredsOfSecond": 0,
        "totalTimeHundredsOfSecond": null,
        "misses": 13,
        "shotsNotFired": 2,
        "timePenalty1Count": null,
        "timePenalty2Count": null,
        "timePenalty3Count": null,
        "timePenalty4Count": null,
        "timePenalty5Count": null,
        "timePenalty6Count": null,
        "targetsCount": null,
        "isMe": null,
        "awardHeader": null
      },
      {
        "id": 3722,
        "name": "Sami Rayes",
        "handleName": "Sami",
        "profileImage": {
          "identityId": 3722,
          "fileId": null,
          "thumbnailUrl": null,
          "previewUrl": null,
          "bigUrl": null,
          "veryBigUrl": null,
          "originalUrl": null,
          "videoOriginalS3Path": null,
          "videoProcessedFolderS3Path": null,
          "videoOriginalUrl": null,
          "videoProcessedFolderUrl": null,
          "videoProcessedAppleUrl": null,
          "videoProcessedAndroidUrl": null,
          "audioUrl": null,
          "audioProcessedUrl": null,
          "audioS3path": null,
          "fileWidth": null,
          "fileHeight": null,
          "fileLength": null,
          "audioSamples": null,
          "fileType": "IMAGE"
        },
        "city": "Saratoga Springs ",
        "state": "Utah",
        "email": "samixrayes-ut@yahoo.com",
        "firstName": "Sami",
        "lastName": "Rayes",
        "divisionName": null,
        "classificationName": null,
        "addedToMatch": null,
        "addedToSquad": null,
        "points": 33000,
        "tieBreakerPoints": 1100,
        "pointsForNonBonusStages": 33000,
        "hundredsOfSecond": 9400,
        "tieBreakerHundredsOfSecond": 9400,
        "squadId": 3839,
        "squadUuid": null,
        "stageId": null,
        "stageUuid": null,
        "divisionId": 13,
        "maxPoints": 54000,
        "stagesProgressCount": 5,
        "stagesCount": 5,
        "shotsProgressCount": 54,
        "maxShots": 54,
        "stageCompleted": null,
        "stageDisqualified": false,
        "matchDisqualified": false,
        "bonusPoints10k": 26000,
        "bonusPoints10kForNonBonusStages": 26000,
        "allSquads": null,
        "allStages": null,
        "categoryIds": null,
        "classificationId": 9,
        "memberNumber": "4922",
        "proSeriesPoints10k": null,
        "requiresTime": null,
        "rank": 9,
        "successRate": null,
        "squad": null,
        "amount": 0,
        "currencyCode": null,
        "formattedAmount": null,
        "paymentSuccessful": null,
        "paymentFailed": null,
        "paymentProcessing": null,
        "paymentRefunded": null,
        "paymentRefundProcessing": null,
        "paymentDate": null,
        "matchShooterId": null,
        "isShootingNow": false,
        "isShootingNext": false,
        "hidden": null,
        "isInTeam": null,
        "teamName": null,
        "shootAsTeam": false,
        "teammateShooterId": null,
        "secondShooter": null,
        "powerFactor": null,
        "isMD": null,
        "isRO": null,
        "countryId": 2,
        "countryCode": "US",
        "dropped": -21000,
        "shirtSize": null,
        "individualName": null,
        "individualHandleName": null,
        "following": false,
        "checkedIn": null,
        "penaltiesHundredsOfSecond": 0,
        "bonusesHundredsOfSecond": 0,
        "totalTimeHundredsOfSecond": null,
        "misses": 21,
        "shotsNotFired": 0,
        "timePenalty1Count": null,
        "timePenalty2Count": null,
        "timePenalty3Count": null,
        "timePenalty4Count": null,
        "timePenalty5Count": null,
        "timePenalty6Count": null,
        "targetsCount": null,
        "isMe": null,
        "awardHeader": null
      },
      {
        "id": 941,
        "name": "Dan Nay",
        "handleName": "DanNay",
        "profileImage": {
          "identityId": 941,
          "fileId": "1763844713482-s9pm7wdy6f0pl81a.jpg",
          "thumbnailUrl": "https://impactscoring-social-bucket-production2.s3.amazonaws.com/profileImages/941/256-1763844713482-s9pm7wdy6f0pl81a.jpg",
          "previewUrl": "https://impactscoring-social-bucket-production2.s3.amazonaws.com/profileImages/941/512-1763844713482-s9pm7wdy6f0pl81a.jpg",
          "bigUrl": "https://impactscoring-social-bucket-production2.s3.amazonaws.com/profileImages/941/1024-1763844713482-s9pm7wdy6f0pl81a.jpg",
          "veryBigUrl": "https://impactscoring-social-bucket-production2.s3.amazonaws.com/profileImages/941/2048-1763844713482-s9pm7wdy6f0pl81a.jpg",
          "originalUrl": "https://impactscoring-social-bucket-production2.s3.amazonaws.com/profileImages/941/original-1763844713482-s9pm7wdy6f0pl81a.jpg",
          "videoOriginalS3Path": null,
          "videoProcessedFolderS3Path": null,
          "videoOriginalUrl": null,
          "videoProcessedFolderUrl": null,
          "videoProcessedAppleUrl": null,
          "videoProcessedAndroidUrl": null,
          "audioUrl": null,
          "audioProcessedUrl": null,
          "audioS3path": null,
          "fileWidth": null,
          "fileHeight": null,
          "fileLength": null,
          "audioSamples": null,
          "fileType": "IMAGE"
        },
        "city": null,
        "state": "Utah",
        "email": "naybear21@gmail.com",
        "firstName": "Dan",
        "lastName": "Nay",
        "divisionName": null,
        "classificationName": null,
        "addedToMatch": null,
        "addedToSquad": null,
        "points": 28000,
        "tieBreakerPoints": 400,
        "pointsForNonBonusStages": 28000,
        "hundredsOfSecond": 10700,
        "tieBreakerHundredsOfSecond": 10700,
        "squadId": 3841,
        "squadUuid": null,
        "stageId": null,
        "stageUuid": null,
        "divisionId": 13,
        "maxPoints": 54000,
        "stagesProgressCount": 5,
        "stagesCount": 5,
        "shotsProgressCount": 52,
        "maxShots": 54,
        "stageCompleted": null,
        "stageDisqualified": false,
        "matchDisqualified": false,
        "bonusPoints10k": 13000,
        "bonusPoints10kForNonBonusStages": 13000,
        "allSquads": null,
        "allStages": null,
        "categoryIds": null,
        "classificationId": 7,
        "memberNumber": "2675",
        "proSeriesPoints10k": null,
        "requiresTime": null,
        "rank": 10,
        "successRate": null,
        "squad": null,
        "amount": 0,
        "currencyCode": null,
        "formattedAmount": null,
        "paymentSuccessful": null,
        "paymentFailed": null,
        "paymentProcessing": null,
        "paymentRefunded": null,
        "paymentRefundProcessing": null,
        "paymentDate": null,
        "matchShooterId": null,
        "isShootingNow": false,
        "isShootingNext": false,
        "hidden": null,
        "isInTeam": null,
        "teamName": null,
        "shootAsTeam": false,
        "teammateShooterId": null,
        "secondShooter": null,
        "powerFactor": null,
        "isMD": null,
        "isRO": null,
        "countryId": 2,
        "countryCode": "US",
        "dropped": -26000,
        "shirtSize": null,
        "individualName": null,
        "individualHandleName": null,
        "following": false,
        "checkedIn": null,
        "penaltiesHundredsOfSecond": 0,
        "bonusesHundredsOfSecond": 0,
        "totalTimeHundredsOfSecond": null,
        "misses": 24,
        "shotsNotFired": 2,
        "timePenalty1Count": null,
        "timePenalty2Count": null,
        "timePenalty3Count": null,
        "timePenalty4Count": null,
        "timePenalty5Count": null,
        "timePenalty6Count": null,
        "targetsCount": null,
        "isMe": null,
        "awardHeader": null
      },
      {
        "id": 842,
        "name": "Yuki Civello",
        "handleName": "Panda",
        "profileImage": {
          "identityId": 842,
          "fileId": null,
          "thumbnailUrl": null,
          "previewUrl": null,
          "bigUrl": null,
          "veryBigUrl": null,
          "originalUrl": null,
          "videoOriginalS3Path": null,
          "videoProcessedFolderS3Path": null,
          "videoOriginalUrl": null,
          "videoProcessedFolderUrl": null,
          "videoProcessedAppleUrl": null,
          "videoProcessedAndroidUrl": null,
          "audioUrl": null,
          "audioProcessedUrl": null,
          "audioS3path": null,
          "fileWidth": null,
          "fileHeight": null,
          "fileLength": null,
          "audioSamples": null,
          "fileType": "IMAGE"
        },
        "city": null,
        "state": null,
        "email": "koyuki.civello@gmail.com",
        "firstName": "Yuki",
        "lastName": "Civello",
        "divisionName": null,
        "classificationName": null,
        "addedToMatch": null,
        "addedToSquad": null,
        "points": 28000,
        "tieBreakerPoints": 0,
        "pointsForNonBonusStages": 28000,
        "hundredsOfSecond": 12000,
        "tieBreakerHundredsOfSecond": 12000,
        "squadId": 3839,
        "squadUuid": null,
        "stageId": null,
        "stageUuid": null,
        "divisionId": 5,
        "maxPoints": 54000,
        "stagesProgressCount": 5,
        "stagesCount": 5,
        "shotsProgressCount": 54,
        "maxShots": 54,
        "stageCompleted": null,
        "stageDisqualified": false,
        "matchDisqualified": false,
        "bonusPoints10k": 0,
        "bonusPoints10kForNonBonusStages": 0,
        "allSquads": null,
        "allStages": null,
        "categoryIds": null,
        "classificationId": 6,
        "memberNumber": "",
        "proSeriesPoints10k": null,
        "requiresTime": null,
        "rank": 11,
        "successRate": null,
        "squad": null,
        "amount": 0,
        "currencyCode": null,
        "formattedAmount": null,
        "paymentSuccessful": null,
        "paymentFailed": null,
        "paymentProcessing": null,
        "paymentRefunded": null,
        "paymentRefundProcessing": null,
        "paymentDate": null,
        "matchShooterId": null,
        "isShootingNow": false,
        "isShootingNext": false,
        "hidden": null,
        "isInTeam": null,
        "teamName": null,
        "shootAsTeam": false,
        "teammateShooterId": null,
        "secondShooter": null,
        "powerFactor": null,
        "isMD": null,
        "isRO": null,
        "countryId": 2,
        "countryCode": "US",
        "dropped": -26000,
        "shirtSize": null,
        "individualName": null,
        "individualHandleName": null,
        "following": false,
        "checkedIn": null,
        "penaltiesHundredsOfSecond": 0,
        "bonusesHundredsOfSecond": 0,
        "totalTimeHundredsOfSecond": null,
        "misses": 26,
        "shotsNotFired": 0,
        "timePenalty1Count": null,
        "timePenalty2Count": null,
        "timePenalty3Count": null,
        "timePenalty4Count": null,
        "timePenalty5Count": null,
        "timePenalty6Count": null,
        "targetsCount": null,
        "isMe": null,
        "awardHeader": null
      },
      {
        "id": 10051,
        "name": "Kaiden Jones",
        "handleName": "Jonesie54",
        "profileImage": {
          "identityId": 10051,
          "fileId": null,
          "thumbnailUrl": null,
          "previewUrl": null,
          "bigUrl": null,
          "veryBigUrl": null,
          "originalUrl": null,
          "videoOriginalS3Path": null,
          "videoProcessedFolderS3Path": null,
          "videoOriginalUrl": null,
          "videoProcessedFolderUrl": null,
          "videoProcessedAppleUrl": null,
          "videoProcessedAndroidUrl": null,
          "audioUrl": null,
          "audioProcessedUrl": null,
          "audioS3path": null,
          "fileWidth": null,
          "fileHeight": null,
          "fileLength": null,
          "audioSamples": null,
          "fileType": "IMAGE"
        },
        "city": null,
        "state": null,
        "email": "kaiden5454@gmail.com",
        "firstName": "Kaiden",
        "lastName": "Jones",
        "divisionName": null,
        "classificationName": null,
        "addedToMatch": null,
        "addedToSquad": null,
        "points": 26000,
        "tieBreakerPoints": 400,
        "pointsForNonBonusStages": 26000,
        "hundredsOfSecond": 12000,
        "tieBreakerHundredsOfSecond": 12000,
        "squadId": 3840,
        "squadUuid": null,
        "stageId": null,
        "stageUuid": null,
        "divisionId": 1,
        "maxPoints": 54000,
        "stagesProgressCount": 5,
        "stagesCount": 5,
        "shotsProgressCount": 54,
        "maxShots": 54,
        "stageCompleted": null,
        "stageDisqualified": false,
        "matchDisqualified": false,
        "bonusPoints10k": 0,
        "bonusPoints10kForNonBonusStages": 0,
        "allSquads": null,
        "allStages": null,
        "categoryIds": null,
        "classificationId": 9,
        "memberNumber": "",
        "proSeriesPoints10k": null,
        "requiresTime": null,
        "rank": 12,
        "successRate": null,
        "squad": null,
        "amount": 0,
        "currencyCode": null,
        "formattedAmount": null,
        "paymentSuccessful": null,
        "paymentFailed": null,
        "paymentProcessing": null,
        "paymentRefunded": null,
        "paymentRefundProcessing": null,
        "paymentDate": null,
        "matchShooterId": null,
        "isShootingNow": false,
        "isShootingNext": false,
        "hidden": null,
        "isInTeam": null,
        "teamName": null,
        "shootAsTeam": false,
        "teammateShooterId": null,
        "secondShooter": null,
        "powerFactor": null,
        "isMD": null,
        "isRO": null,
        "countryId": 2,
        "countryCode": "US",
        "dropped": -28000,
        "shirtSize": null,
        "individualName": null,
        "individualHandleName": null,
        "following": false,
        "checkedIn": null,
        "penaltiesHundredsOfSecond": 0,
        "bonusesHundredsOfSecond": 0,
        "totalTimeHundredsOfSecond": null,
        "misses": 28,
        "shotsNotFired": 0,
        "timePenalty1Count": null,
        "timePenalty2Count": null,
        "timePenalty3Count": null,
        "timePenalty4Count": null,
        "timePenalty5Count": null,
        "timePenalty6Count": null,
        "targetsCount": null,
        "isMe": null,
        "awardHeader": null
      },
      {
        "id": 11856,
        "name": "Jason Wilson",
        "handleName": "BLANK",
        "profileImage": {
          "identityId": 11856,
          "fileId": null,
          "thumbnailUrl": null,
          "previewUrl": null,
          "bigUrl": null,
          "veryBigUrl": null,
          "originalUrl": null,
          "videoOriginalS3Path": null,
          "videoProcessedFolderS3Path": null,
          "videoOriginalUrl": null,
          "videoProcessedFolderUrl": null,
          "videoProcessedAppleUrl": null,
          "videoProcessedAndroidUrl": null,
          "audioUrl": null,
          "audioProcessedUrl": null,
          "audioS3path": null,
          "fileWidth": null,
          "fileHeight": null,
          "fileLength": null,
          "audioSamples": null,
          "fileType": "IMAGE"
        },
        "city": null,
        "state": null,
        "email": "wil63vw@gmail.com",
        "firstName": "Jason",
        "lastName": "Wilson",
        "divisionName": null,
        "classificationName": null,
        "addedToMatch": null,
        "addedToSquad": null,
        "points": 23000,
        "tieBreakerPoints": 1100,
        "pointsForNonBonusStages": 23000,
        "hundredsOfSecond": 11800,
        "tieBreakerHundredsOfSecond": 11800,
        "squadId": 3840,
        "squadUuid": null,
        "stageId": null,
        "stageUuid": null,
        "divisionId": 13,
        "maxPoints": 54000,
        "stagesProgressCount": 5,
        "stagesCount": 5,
        "shotsProgressCount": 54,
        "maxShots": 54,
        "stageCompleted": null,
        "stageDisqualified": false,
        "matchDisqualified": false,
        "bonusPoints10k": 2000,
        "bonusPoints10kForNonBonusStages": 2000,
        "allSquads": null,
        "allStages": null,
        "categoryIds": null,
        "classificationId": 9,
        "memberNumber": "311",
        "proSeriesPoints10k": null,
        "requiresTime": null,
        "rank": 13,
        "successRate": null,
        "squad": null,
        "amount": 0,
        "currencyCode": null,
        "formattedAmount": null,
        "paymentSuccessful": null,
        "paymentFailed": null,
        "paymentProcessing": null,
        "paymentRefunded": null,
        "paymentRefundProcessing": null,
        "paymentDate": null,
        "matchShooterId": null,
        "isShootingNow": false,
        "isShootingNext": false,
        "hidden": null,
        "isInTeam": null,
        "teamName": null,
        "shootAsTeam": false,
        "teammateShooterId": null,
        "secondShooter": null,
        "powerFactor": null,
        "isMD": null,
        "isRO": null,
        "countryId": 2,
        "countryCode": "US",
        "dropped": -31000,
        "shirtSize": null,
        "individualName": null,
        "individualHandleName": null,
        "following": false,
        "checkedIn": null,
        "penaltiesHundredsOfSecond": 0,
        "bonusesHundredsOfSecond": 0,
        "totalTimeHundredsOfSecond": null,
        "misses": 31,
        "shotsNotFired": 0,
        "timePenalty1Count": null,
        "timePenalty2Count": null,
        "timePenalty3Count": null,
        "timePenalty4Count": null,
        "timePenalty5Count": null,
        "timePenalty6Count": null,
        "targetsCount": null,
        "isMe": null,
        "awardHeader": null
      },
      {
        "id": 11836,
        "name": "Alexus Winter",
        "handleName": "Lexi",
        "profileImage": {
          "identityId": 11836,
          "fileId": "1761362634995-omrr5bmcz4gnm2mj.jpg",
          "thumbnailUrl": "https://impactscoring-social-bucket-production2.s3.amazonaws.com/profileImages/11836/256-1761362634995-omrr5bmcz4gnm2mj.jpg",
          "previewUrl": "https://impactscoring-social-bucket-production2.s3.amazonaws.com/profileImages/11836/512-1761362634995-omrr5bmcz4gnm2mj.jpg",
          "bigUrl": "https://impactscoring-social-bucket-production2.s3.amazonaws.com/profileImages/11836/1024-1761362634995-omrr5bmcz4gnm2mj.jpg",
          "veryBigUrl": "https://impactscoring-social-bucket-production2.s3.amazonaws.com/profileImages/11836/2048-1761362634995-omrr5bmcz4gnm2mj.jpg",
          "originalUrl": "https://impactscoring-social-bucket-production2.s3.amazonaws.com/profileImages/11836/original-1761362634995-omrr5bmcz4gnm2mj.jpg",
          "videoOriginalS3Path": null,
          "videoProcessedFolderS3Path": null,
          "videoOriginalUrl": null,
          "videoProcessedFolderUrl": null,
          "videoProcessedAppleUrl": null,
          "videoProcessedAndroidUrl": null,
          "audioUrl": null,
          "audioProcessedUrl": null,
          "audioS3path": null,
          "fileWidth": null,
          "fileHeight": null,
          "fileLength": null,
          "audioSamples": null,
          "fileType": "IMAGE"
        },
        "city": null,
        "state": null,
        "email": "alexusrubywinter@gmail.com",
        "firstName": "Alexus",
        "lastName": "Winter",
        "divisionName": null,
        "classificationName": null,
        "addedToMatch": null,
        "addedToSquad": null,
        "points": 23000,
        "tieBreakerPoints": 900,
        "pointsForNonBonusStages": 23000,
        "hundredsOfSecond": 12000,
        "tieBreakerHundredsOfSecond": 12000,
        "squadId": 3840,
        "squadUuid": null,
        "stageId": null,
        "stageUuid": null,
        "divisionId": 5,
        "maxPoints": 54000,
        "stagesProgressCount": 5,
        "stagesCount": 5,
        "shotsProgressCount": 54,
        "maxShots": 54,
        "stageCompleted": null,
        "stageDisqualified": false,
        "matchDisqualified": false,
        "bonusPoints10k": 0,
        "bonusPoints10kForNonBonusStages": 0,
        "allSquads": null,
        "allStages": null,
        "categoryIds": null,
        "classificationId": 9,
        "memberNumber": "",
        "proSeriesPoints10k": null,
        "requiresTime": null,
        "rank": 14,
        "successRate": null,
        "squad": null,
        "amount": 0,
        "currencyCode": null,
        "formattedAmount": null,
        "paymentSuccessful": null,
        "paymentFailed": null,
        "paymentProcessing": null,
        "paymentRefunded": null,
        "paymentRefundProcessing": null,
        "paymentDate": null,
        "matchShooterId": null,
        "isShootingNow": false,
        "isShootingNext": false,
        "hidden": null,
        "isInTeam": null,
        "teamName": null,
        "shootAsTeam": false,
        "teammateShooterId": null,
        "secondShooter": null,
        "powerFactor": null,
        "isMD": null,
        "isRO": null,
        "countryId": null,
        "countryCode": null,
        "dropped": -31000,
        "shirtSize": null,
        "individualName": null,
        "individualHandleName": null,
        "following": false,
        "checkedIn": null,
        "penaltiesHundredsOfSecond": 0,
        "bonusesHundredsOfSecond": 0,
        "totalTimeHundredsOfSecond": null,
        "misses": 31,
        "shotsNotFired": 0,
        "timePenalty1Count": null,
        "timePenalty2Count": null,
        "timePenalty3Count": null,
        "timePenalty4Count": null,
        "timePenalty5Count": null,
        "timePenalty6Count": null,
        "targetsCount": null,
        "isMe": null,
        "awardHeader": null
      },
      {
        "id": 6965,
        "name": "Ethan Kikuchi",
        "handleName": "EthanK",
        "profileImage": {
          "identityId": 6965,
          "fileId": "1766934607386-edqk3lnw4gzefn3d.jpg",
          "thumbnailUrl": "https://impactscoring-social-bucket-production2.s3.amazonaws.com/profileImages/6965/256-1766934607386-edqk3lnw4gzefn3d.jpg",
          "previewUrl": "https://impactscoring-social-bucket-production2.s3.amazonaws.com/profileImages/6965/512-1766934607386-edqk3lnw4gzefn3d.jpg",
          "bigUrl": "https://impactscoring-social-bucket-production2.s3.amazonaws.com/profileImages/6965/1024-1766934607386-edqk3lnw4gzefn3d.jpg",
          "veryBigUrl": "https://impactscoring-social-bucket-production2.s3.amazonaws.com/profileImages/6965/2048-1766934607386-edqk3lnw4gzefn3d.jpg",
          "originalUrl": "https://impactscoring-social-bucket-production2.s3.amazonaws.com/profileImages/6965/original-1766934607386-edqk3lnw4gzefn3d.jpg",
          "videoOriginalS3Path": null,
          "videoProcessedFolderS3Path": null,
          "videoOriginalUrl": null,
          "videoProcessedFolderUrl": null,
          "videoProcessedAppleUrl": null,
          "videoProcessedAndroidUrl": null,
          "audioUrl": null,
          "audioProcessedUrl": null,
          "audioS3path": null,
          "fileWidth": null,
          "fileHeight": null,
          "fileLength": null,
          "audioSamples": null,
          "fileType": "IMAGE"
        },
        "city": null,
        "state": null,
        "email": "ejkikuchi@gmail.com",
        "firstName": "Ethan",
        "lastName": "Kikuchi",
        "divisionName": null,
        "classificationName": null,
        "addedToMatch": null,
        "addedToSquad": null,
        "points": 15000,
        "tieBreakerPoints": 600,
        "pointsForNonBonusStages": 15000,
        "hundredsOfSecond": 8500,
        "tieBreakerHundredsOfSecond": 8500,
        "squadId": 3842,
        "squadUuid": null,
        "stageId": null,
        "stageUuid": null,
        "divisionId": 1,
        "maxPoints": 54000,
        "stagesProgressCount": 5,
        "stagesCount": 5,
        "shotsProgressCount": 51,
        "maxShots": 54,
        "stageCompleted": null,
        "stageDisqualified": false,
        "matchDisqualified": false,
        "bonusPoints10k": 35000,
        "bonusPoints10kForNonBonusStages": 35000,
        "allSquads": null,
        "allStages": null,
        "categoryIds": null,
        "classificationId": 9,
        "memberNumber": " ",
        "proSeriesPoints10k": null,
        "requiresTime": null,
        "rank": 15,
        "successRate": null,
        "squad": null,
        "amount": 0,
        "currencyCode": null,
        "formattedAmount": null,
        "paymentSuccessful": null,
        "paymentFailed": null,
        "paymentProcessing": null,
        "paymentRefunded": null,
        "paymentRefundProcessing": null,
        "paymentDate": null,
        "matchShooterId": null,
        "isShootingNow": false,
        "isShootingNext": false,
        "hidden": null,
        "isInTeam": null,
        "teamName": null,
        "shootAsTeam": false,
        "teammateShooterId": null,
        "secondShooter": null,
        "powerFactor": null,
        "isMD": null,
        "isRO": null,
        "countryId": 2,
        "countryCode": "US",
        "dropped": -39000,
        "shirtSize": null,
        "individualName": null,
        "individualHandleName": null,
        "following": false,
        "checkedIn": null,
        "penaltiesHundredsOfSecond": 0,
        "bonusesHundredsOfSecond": 0,
        "totalTimeHundredsOfSecond": null,
        "misses": 36,
        "shotsNotFired": 3,
        "timePenalty1Count": null,
        "timePenalty2Count": null,
        "timePenalty3Count": null,
        "timePenalty4Count": null,
        "timePenalty5Count": null,
        "timePenalty6Count": null,
        "targetsCount": null,
        "isMe": null,
        "awardHeader": null
      },
      {
        "id": 11326,
        "name": "Michael Harlow",
        "handleName": "Dadisdabest",
        "profileImage": {
          "identityId": 11326,
          "fileId": null,
          "thumbnailUrl": null,
          "previewUrl": null,
          "bigUrl": null,
          "veryBigUrl": null,
          "originalUrl": null,
          "videoOriginalS3Path": null,
          "videoProcessedFolderS3Path": null,
          "videoOriginalUrl": null,
          "videoProcessedFolderUrl": null,
          "videoProcessedAppleUrl": null,
          "videoProcessedAndroidUrl": null,
          "audioUrl": null,
          "audioProcessedUrl": null,
          "audioS3path": null,
          "fileWidth": null,
          "fileHeight": null,
          "fileLength": null,
          "audioSamples": null,
          "fileType": "IMAGE"
        },
        "city": null,
        "state": null,
        "email": "harlowmr@gmail.com",
        "firstName": "Michael",
        "lastName": "Harlow",
        "divisionName": null,
        "classificationName": null,
        "addedToMatch": null,
        "addedToSquad": null,
        "points": 13000,
        "tieBreakerPoints": 700,
        "pointsForNonBonusStages": 13000,
        "hundredsOfSecond": 12000,
        "tieBreakerHundredsOfSecond": 12000,
        "squadId": 3842,
        "squadUuid": null,
        "stageId": null,
        "stageUuid": null,
        "divisionId": 13,
        "maxPoints": 54000,
        "stagesProgressCount": 5,
        "stagesCount": 5,
        "shotsProgressCount": 36,
        "maxShots": 54,
        "stageCompleted": null,
        "stageDisqualified": false,
        "matchDisqualified": false,
        "bonusPoints10k": 0,
        "bonusPoints10kForNonBonusStages": 0,
        "allSquads": null,
        "allStages": null,
        "categoryIds": null,
        "classificationId": 9,
        "memberNumber": "",
        "proSeriesPoints10k": null,
        "requiresTime": null,
        "rank": 16,
        "successRate": null,
        "squad": null,
        "amount": 0,
        "currencyCode": null,
        "formattedAmount": null,
        "paymentSuccessful": null,
        "paymentFailed": null,
        "paymentProcessing": null,
        "paymentRefunded": null,
        "paymentRefundProcessing": null,
        "paymentDate": null,
        "matchShooterId": null,
        "isShootingNow": false,
        "isShootingNext": false,
        "hidden": null,
        "isInTeam": null,
        "teamName": null,
        "shootAsTeam": false,
        "teammateShooterId": null,
        "secondShooter": null,
        "powerFactor": null,
        "isMD": null,
        "isRO": null,
        "countryId": 2,
        "countryCode": "US",
        "dropped": -41000,
        "shirtSize": null,
        "individualName": null,
        "individualHandleName": null,
        "following": false,
        "checkedIn": null,
        "penaltiesHundredsOfSecond": 0,
        "bonusesHundredsOfSecond": 0,
        "totalTimeHundredsOfSecond": null,
        "misses": 23,
        "shotsNotFired": 18,
        "timePenalty1Count": null,
        "timePenalty2Count": null,
        "timePenalty3Count": null,
        "timePenalty4Count": null,
        "timePenalty5Count": null,
        "timePenalty6Count": null,
        "targetsCount": null,
        "isMe": null,
        "awardHeader": null
      },
      {
        "id": 6044,
        "name": "John C Scranton",
        "handleName": "Tooltech",
        "profileImage": {
          "identityId": 6044,
          "fileId": null,
          "thumbnailUrl": null,
          "previewUrl": null,
          "bigUrl": null,
          "veryBigUrl": null,
          "originalUrl": null,
          "videoOriginalS3Path": null,
          "videoProcessedFolderS3Path": null,
          "videoOriginalUrl": null,
          "videoProcessedFolderUrl": null,
          "videoProcessedAppleUrl": null,
          "videoProcessedAndroidUrl": null,
          "audioUrl": null,
          "audioProcessedUrl": null,
          "audioS3path": null,
          "fileWidth": null,
          "fileHeight": null,
          "fileLength": null,
          "audioSamples": null,
          "fileType": "IMAGE"
        },
        "city": null,
        "state": null,
        "email": "tooltech.stw@gmail.com",
        "firstName": "John C",
        "lastName": "Scranton",
        "divisionName": null,
        "classificationName": null,
        "addedToMatch": null,
        "addedToSquad": null,
        "points": 12000,
        "tieBreakerPoints": 200,
        "pointsForNonBonusStages": 12000,
        "hundredsOfSecond": 12000,
        "tieBreakerHundredsOfSecond": 12000,
        "squadId": 3839,
        "squadUuid": null,
        "stageId": null,
        "stageUuid": null,
        "divisionId": 6,
        "maxPoints": 54000,
        "stagesProgressCount": 5,
        "stagesCount": 5,
        "shotsProgressCount": 54,
        "maxShots": 54,
        "stageCompleted": null,
        "stageDisqualified": false,
        "matchDisqualified": false,
        "bonusPoints10k": 0,
        "bonusPoints10kForNonBonusStages": 0,
        "allSquads": null,
        "allStages": null,
        "categoryIds": null,
        "classificationId": 9,
        "memberNumber": "4923",
        "proSeriesPoints10k": null,
        "requiresTime": null,
        "rank": 17,
        "successRate": null,
        "squad": null,
        "amount": 0,
        "currencyCode": null,
        "formattedAmount": null,
        "paymentSuccessful": null,
        "paymentFailed": null,
        "paymentProcessing": null,
        "paymentRefunded": null,
        "paymentRefundProcessing": null,
        "paymentDate": null,
        "matchShooterId": null,
        "isShootingNow": false,
        "isShootingNext": false,
        "hidden": null,
        "isInTeam": null,
        "teamName": null,
        "shootAsTeam": false,
        "teammateShooterId": null,
        "secondShooter": null,
        "powerFactor": null,
        "isMD": null,
        "isRO": null,
        "countryId": 2,
        "countryCode": "US",
        "dropped": -42000,
        "shirtSize": null,
        "individualName": null,
        "individualHandleName": null,
        "following": false,
        "checkedIn": null,
        "penaltiesHundredsOfSecond": 0,
        "bonusesHundredsOfSecond": 0,
        "totalTimeHundredsOfSecond": null,
        "misses": 42,
        "shotsNotFired": 0,
        "timePenalty1Count": null,
        "timePenalty2Count": null,
        "timePenalty3Count": null,
        "timePenalty4Count": null,
        "timePenalty5Count": null,
        "timePenalty6Count": null,
        "targetsCount": null,
        "isMe": null,
        "awardHeader": null
      },
      {
        "id": 10111,
        "name": "Rick Engellant ",
        "handleName": "GrandpaRick",
        "profileImage": {
          "identityId": 10111,
          "fileId": null,
          "thumbnailUrl": null,
          "previewUrl": null,
          "bigUrl": null,
          "veryBigUrl": null,
          "originalUrl": null,
          "videoOriginalS3Path": null,
          "videoProcessedFolderS3Path": null,
          "videoOriginalUrl": null,
          "videoProcessedFolderUrl": null,
          "videoProcessedAppleUrl": null,
          "videoProcessedAndroidUrl": null,
          "audioUrl": null,
          "audioProcessedUrl": null,
          "audioS3path": null,
          "fileWidth": null,
          "fileHeight": null,
          "fileLength": null,
          "audioSamples": null,
          "fileType": "IMAGE"
        },
        "city": null,
        "state": null,
        "email": "rickengellant@outlook.com",
        "firstName": "Rick",
        "lastName": "Engellant ",
        "divisionName": null,
        "classificationName": null,
        "addedToMatch": null,
        "addedToSquad": null,
        "points": 10000,
        "tieBreakerPoints": 300,
        "pointsForNonBonusStages": 10000,
        "hundredsOfSecond": 12000,
        "tieBreakerHundredsOfSecond": 12000,
        "squadId": 3840,
        "squadUuid": null,
        "stageId": null,
        "stageUuid": null,
        "divisionId": 6,
        "maxPoints": 54000,
        "stagesProgressCount": 5,
        "stagesCount": 5,
        "shotsProgressCount": 54,
        "maxShots": 54,
        "stageCompleted": null,
        "stageDisqualified": false,
        "matchDisqualified": false,
        "bonusPoints10k": 0,
        "bonusPoints10kForNonBonusStages": 0,
        "allSquads": null,
        "allStages": null,
        "categoryIds": null,
        "classificationId": 9,
        "memberNumber": "5404",
        "proSeriesPoints10k": null,
        "requiresTime": null,
        "rank": 18,
        "successRate": null,
        "squad": null,
        "amount": 0,
        "currencyCode": null,
        "formattedAmount": null,
        "paymentSuccessful": null,
        "paymentFailed": null,
        "paymentProcessing": null,
        "paymentRefunded": null,
        "paymentRefundProcessing": null,
        "paymentDate": null,
        "matchShooterId": null,
        "isShootingNow": false,
        "isShootingNext": false,
        "hidden": null,
        "isInTeam": null,
        "teamName": null,
        "shootAsTeam": false,
        "teammateShooterId": null,
        "secondShooter": null,
        "powerFactor": null,
        "isMD": null,
        "isRO": null,
        "countryId": 2,
        "countryCode": "US",
        "dropped": -44000,
        "shirtSize": null,
        "individualName": null,
        "individualHandleName": null,
        "following": false,
        "checkedIn": null,
        "penaltiesHundredsOfSecond": 0,
        "bonusesHundredsOfSecond": 0,
        "totalTimeHundredsOfSecond": null,
        "misses": 44,
        "shotsNotFired": 0,
        "timePenalty1Count": null,
        "timePenalty2Count": null,
        "timePenalty3Count": null,
        "timePenalty4Count": null,
        "timePenalty5Count": null,
        "timePenalty6Count": null,
        "targetsCount": null,
        "isMe": null,
        "awardHeader": null
      },
      {
        "id": 11824,
        "name": "Ronald Nay",
        "handleName": "Gunnisonkidd",
        "profileImage": {
          "identityId": 11824,
          "fileId": null,
          "thumbnailUrl": null,
          "previewUrl": null,
          "bigUrl": null,
          "veryBigUrl": null,
          "originalUrl": null,
          "videoOriginalS3Path": null,
          "videoProcessedFolderS3Path": null,
          "videoOriginalUrl": null,
          "videoProcessedFolderUrl": null,
          "videoProcessedAppleUrl": null,
          "videoProcessedAndroidUrl": null,
          "audioUrl": null,
          "audioProcessedUrl": null,
          "audioS3path": null,
          "fileWidth": null,
          "fileHeight": null,
          "fileLength": null,
          "audioSamples": null,
          "fileType": "IMAGE"
        },
        "city": null,
        "state": null,
        "email": "ronaldnay@gmail.com",
        "firstName": "Ronald",
        "lastName": "Nay",
        "divisionName": null,
        "classificationName": null,
        "addedToMatch": null,
        "addedToSquad": null,
        "points": 7000,
        "tieBreakerPoints": 0,
        "pointsForNonBonusStages": 7000,
        "hundredsOfSecond": 12000,
        "tieBreakerHundredsOfSecond": 12000,
        "squadId": 3841,
        "squadUuid": null,
        "stageId": null,
        "stageUuid": null,
        "divisionId": 6,
        "maxPoints": 54000,
        "stagesProgressCount": 5,
        "stagesCount": 5,
        "shotsProgressCount": 33,
        "maxShots": 54,
        "stageCompleted": null,
        "stageDisqualified": false,
        "matchDisqualified": false,
        "bonusPoints10k": 0,
        "bonusPoints10kForNonBonusStages": 0,
        "allSquads": null,
        "allStages": null,
        "categoryIds": null,
        "classificationId": 9,
        "memberNumber": "",
        "proSeriesPoints10k": null,
        "requiresTime": null,
        "rank": 19,
        "successRate": null,
        "squad": null,
        "amount": 0,
        "currencyCode": null,
        "formattedAmount": null,
        "paymentSuccessful": null,
        "paymentFailed": null,
        "paymentProcessing": null,
        "paymentRefunded": null,
        "paymentRefundProcessing": null,
        "paymentDate": null,
        "matchShooterId": null,
        "isShootingNow": false,
        "isShootingNext": false,
        "hidden": null,
        "isInTeam": null,
        "teamName": null,
        "shootAsTeam": false,
        "teammateShooterId": null,
        "secondShooter": null,
        "powerFactor": null,
        "isMD": null,
        "isRO": null,
        "countryId": 2,
        "countryCode": "US",
        "dropped": -47000,
        "shirtSize": null,
        "individualName": null,
        "individualHandleName": null,
        "following": false,
        "checkedIn": null,
        "penaltiesHundredsOfSecond": 0,
        "bonusesHundredsOfSecond": 0,
        "totalTimeHundredsOfSecond": null,
        "misses": 26,
        "shotsNotFired": 21,
        "timePenalty1Count": null,
        "timePenalty2Count": null,
        "timePenalty3Count": null,
        "timePenalty4Count": null,
        "timePenalty5Count": null,
        "timePenalty6Count": null,
        "targetsCount": null,
        "isMe": null,
        "awardHeader": null
      },
      {
        "id": 11340,
        "name": "Steven Harlow",
        "handleName": "FoxySteve",
        "profileImage": {
          "identityId": 11340,
          "fileId": null,
          "thumbnailUrl": null,
          "previewUrl": null,
          "bigUrl": null,
          "veryBigUrl": null,
          "originalUrl": null,
          "videoOriginalS3Path": null,
          "videoProcessedFolderS3Path": null,
          "videoOriginalUrl": null,
          "videoProcessedFolderUrl": null,
          "videoProcessedAppleUrl": null,
          "videoProcessedAndroidUrl": null,
          "audioUrl": null,
          "audioProcessedUrl": null,
          "audioS3path": null,
          "fileWidth": null,
          "fileHeight": null,
          "fileLength": null,
          "audioSamples": null,
          "fileType": "IMAGE"
        },
        "city": null,
        "state": null,
        "email": "michael.harlow@vca.com",
        "firstName": "Steven",
        "lastName": "Harlow",
        "divisionName": null,
        "classificationName": null,
        "addedToMatch": null,
        "addedToSquad": null,
        "points": 2000,
        "tieBreakerPoints": 0,
        "pointsForNonBonusStages": 2000,
        "hundredsOfSecond": 12000,
        "tieBreakerHundredsOfSecond": 12000,
        "squadId": 3842,
        "squadUuid": null,
        "stageId": null,
        "stageUuid": null,
        "divisionId": 7,
        "maxPoints": 54000,
        "stagesProgressCount": 5,
        "stagesCount": 5,
        "shotsProgressCount": 14,
        "maxShots": 54,
        "stageCompleted": null,
        "stageDisqualified": false,
        "matchDisqualified": false,
        "bonusPoints10k": 0,
        "bonusPoints10kForNonBonusStages": 0,
        "allSquads": null,
        "allStages": null,
        "categoryIds": null,
        "classificationId": 9,
        "memberNumber": "",
        "proSeriesPoints10k": null,
        "requiresTime": null,
        "rank": 20,
        "successRate": null,
        "squad": null,
        "amount": 0,
        "currencyCode": null,
        "formattedAmount": null,
        "paymentSuccessful": null,
        "paymentFailed": null,
        "paymentProcessing": null,
        "paymentRefunded": null,
        "paymentRefundProcessing": null,
        "paymentDate": null,
        "matchShooterId": null,
        "isShootingNow": false,
        "isShootingNext": false,
        "hidden": null,
        "isInTeam": null,
        "teamName": null,
        "shootAsTeam": false,
        "teammateShooterId": null,
        "secondShooter": null,
        "powerFactor": null,
        "isMD": null,
        "isRO": null,
        "countryId": null,
        "countryCode": null,
        "dropped": -52000,
        "shirtSize": null,
        "individualName": null,
        "individualHandleName": null,
        "following": false,
        "checkedIn": null,
        "penaltiesHundredsOfSecond": 0,
        "bonusesHundredsOfSecond": 0,
        "totalTimeHundredsOfSecond": null,
        "misses": 12,
        "shotsNotFired": 40,
        "timePenalty1Count": null,
        "timePenalty2Count": null,
        "timePenalty3Count": null,
        "timePenalty4Count": null,
        "timePenalty5Count": null,
        "timePenalty6Count": null,
        "targetsCount": null,
        "isMe": null,
        "awardHeader": null
      }
    ],
    "divisions": [
      {
        "id": 1,
        "name": "Open",
        "isCustom": false
      },
      {
        "id": 13,
        "name": "Base",
        "isCustom": false
      },
      {
        "id": 5,
        "name": "Ladies",
        "isCustom": false
      },
      {
        "id": 7,
        "name": "Young Guns",
        "isCustom": false
      },
      {
        "id": 6,
        "name": "Old Guns",
        "isCustom": false
      },
      {
        "id": 14,
        "name": "Air Rifle",
        "isCustom": false
      },
      {
        "id": 15,
        "name": "Adaptive",
        "isCustom": false
      },
      {
        "id": 3,
        "name": "Semi-Auto",
        "isCustom": false
      }
    ],
    "stages": [
      {
        "id": 5836,
        "name": "Stage 1",
        "requiresTime": false,
        "tieBreaker": false,
        "maxPoints": 1200,
        "creationDate": "2025-10-08T03:37:12.000+00:00",
        "matchId": 1285,
        "deleted": false,
        "targetsCount": 12,
        "maxTimeHundredsOfSecond": 12000,
        "bonusStage": false,
        "uuid": "c12c6a05-3b1a-48ba-b69d-f3dbdc55b32e",
        "orderingPriority": 0,
        "freeShots": 0,
        "excludedPenaltyUuids": null,
        "hundredsOfSecond": null,
        "points": null,
        "bonusPoints10k": null,
        "shotsProgressCount": null,
        "maxShots": null,
        "completed": null,
        "disqualified": null,
        "dropped": null,
        "penaltiesHundredsOfSecond": null,
        "bonusesHundredsOfSecond": null,
        "totalTimeHundredsOfSecond": null,
        "misses": null,
        "shotsNotFired": null,
        "timePenalty1Count": null,
        "timePenalty2Count": null,
        "timePenalty3Count": null,
        "timePenalty4Count": null,
        "timePenalty5Count": null,
        "timePenalty6Count": null
      },
      {
        "id": 5837,
        "name": "Stage 2",
        "requiresTime": false,
        "tieBreaker": false,
        "maxPoints": 1000,
        "creationDate": "2025-10-08T03:37:19.000+00:00",
        "matchId": 1285,
        "deleted": false,
        "targetsCount": 10,
        "maxTimeHundredsOfSecond": 12000,
        "bonusStage": false,
        "uuid": "6e66222c-6cc9-4624-b1ea-a3edd8666fe0",
        "orderingPriority": 0,
        "freeShots": 0,
        "excludedPenaltyUuids": null,
        "hundredsOfSecond": null,
        "points": null,
        "bonusPoints10k": null,
        "shotsProgressCount": null,
        "maxShots": null,
        "completed": null,
        "disqualified": null,
        "dropped": null,
        "penaltiesHundredsOfSecond": null,
        "bonusesHundredsOfSecond": null,
        "totalTimeHundredsOfSecond": null,
        "misses": null,
        "shotsNotFired": null,
        "timePenalty1Count": null,
        "timePenalty2Count": null,
        "timePenalty3Count": null,
        "timePenalty4Count": null,
        "timePenalty5Count": null,
        "timePenalty6Count": null
      },
      {
        "id": 5838,
        "name": "Stage 3",
        "requiresTime": true,
        "tieBreaker": true,
        "maxPoints": 1200,
        "creationDate": "2025-10-08T03:37:28.000+00:00",
        "matchId": 1285,
        "deleted": false,
        "targetsCount": 12,
        "maxTimeHundredsOfSecond": 12000,
        "bonusStage": false,
        "uuid": "d9f5862a-4e57-4814-936c-2067068ea92b",
        "orderingPriority": 0,
        "freeShots": 0,
        "excludedPenaltyUuids": null,
        "hundredsOfSecond": null,
        "points": null,
        "bonusPoints10k": null,
        "shotsProgressCount": null,
        "maxShots": null,
        "completed": null,
        "disqualified": null,
        "dropped": null,
        "penaltiesHundredsOfSecond": null,
        "bonusesHundredsOfSecond": null,
        "totalTimeHundredsOfSecond": null,
        "misses": null,
        "shotsNotFired": null,
        "timePenalty1Count": null,
        "timePenalty2Count": null,
        "timePenalty3Count": null,
        "timePenalty4Count": null,
        "timePenalty5Count": null,
        "timePenalty6Count": null
      },
      {
        "id": 5839,
        "name": "Stage 4",
        "requiresTime": false,
        "tieBreaker": false,
        "maxPoints": 1000,
        "creationDate": "2025-10-08T03:37:36.000+00:00",
        "matchId": 1285,
        "deleted": false,
        "targetsCount": 10,
        "maxTimeHundredsOfSecond": 12000,
        "bonusStage": false,
        "uuid": "77b67e46-7960-44fb-820a-aa27231a2e4b",
        "orderingPriority": 0,
        "freeShots": 0,
        "excludedPenaltyUuids": null,
        "hundredsOfSecond": null,
        "points": null,
        "bonusPoints10k": null,
        "shotsProgressCount": null,
        "maxShots": null,
        "completed": null,
        "disqualified": null,
        "dropped": null,
        "penaltiesHundredsOfSecond": null,
        "bonusesHundredsOfSecond": null,
        "totalTimeHundredsOfSecond": null,
        "misses": null,
        "shotsNotFired": null,
        "timePenalty1Count": null,
        "timePenalty2Count": null,
        "timePenalty3Count": null,
        "timePenalty4Count": null,
        "timePenalty5Count": null,
        "timePenalty6Count": null
      },
      {
        "id": 5840,
        "name": "Stage 5",
        "requiresTime": false,
        "tieBreaker": false,
        "maxPoints": 1000,
        "creationDate": "2025-10-08T03:37:42.000+00:00",
        "matchId": 1285,
        "deleted": false,
        "targetsCount": 10,
        "maxTimeHundredsOfSecond": 12000,
        "bonusStage": false,
        "uuid": "df8e0b2d-12be-4387-9ce9-4ca90036d3f3",
        "orderingPriority": 0,
        "freeShots": 0,
        "excludedPenaltyUuids": null,
        "hundredsOfSecond": null,
        "points": null,
        "bonusPoints10k": null,
        "shotsProgressCount": null,
        "maxShots": null,
        "completed": null,
        "disqualified": null,
        "dropped": null,
        "penaltiesHundredsOfSecond": null,
        "bonusesHundredsOfSecond": null,
        "totalTimeHundredsOfSecond": null,
        "misses": null,
        "shotsNotFired": null,
        "timePenalty1Count": null,
        "timePenalty2Count": null,
        "timePenalty3Count": null,
        "timePenalty4Count": null,
        "timePenalty5Count": null,
        "timePenalty6Count": null
      }
    ],
    "categories": [],
    "classifications": [
      {
        "id": 5,
        "name": "Expert",
        "hexColor": "1E90FF",
        "isCustom": false
      },
      {
        "id": 6,
        "name": "Sharpshooter",
        "hexColor": "32CD32",
        "isCustom": false
      },
      {
        "id": 7,
        "name": "Marksman",
        "hexColor": "FF8C00",
        "isCustom": false
      },
      {
        "id": 8,
        "name": "Novice",
        "hexColor": "8A2BE2",
        "isCustom": false
      },
      {
        "id": 9,
        "name": "Unclassed",
        "hexColor": "FFFFFF",
        "isCustom": false
      }
    ],
    "countries": [
      {
        "id": 2,
        "name": "United States",
        "code": "US"
      }
    ],
    "defaultClassificationId": 9,
    "hasBonusStages": false,
    "allowsBonusStages": true,
    "hasParTimeBonus": true,
    "hasMultiplier": true,
    "hasProPoints": false,
    "hasScoreColumn": true,
    "allowsSortingByNrl22Total": false,
    "allowTeams": false,
    "powerFactorTieBreaker": false,
    "impactsColumnName": "MATCH TOTAL",
    "impactsWithoutBonusColumnName": null,
    "proPointsColumnName": null,
    "matchMaxPoints": 54000,
    "timePlus": false,
    "secretResultsShooterIdFollowed": null,
    "secretResultsStageName": null
  },
  "errorLabel": "SUCCESS"
}